{
    "title": "Facials",
    "fields": [
        {
            "name": "Basic",
            "price": "£43.00"
        },
        {
            "name": "Prescriptive",
            "price": "£49.50",
            "note": "Nourishing, balancing and re-mineralising, perfect choice to suit all skin types."
        },
        {
            "name": "Black Mud",
            "price": "£52.00",
            "note": "Deap cleansing, anti-bacterial and refining, stimulates and brightens the complexion."
        },
        {
            "name": "Algimud",
            "price": "£55.00",
            "note": "A combination of Dead Sea Mud and Alginates creating a unique formula with exceptional properties for total skin renewal"
        }
    ]
}
